ResiSim/Data_Generation.py
ResiSim/Main.py
ResiSim/__init__.py
ResiSim/credentials.json
ResiSim/weather.txt
ResiSim-2.0.9.dist-info/LICENSE
ResiSim-2.0.9.dist-info/METADATA
ResiSim-2.0.9.dist-info/WHEEL
ResiSim-2.0.9.dist-info/top_level.txt
ResiSim-2.0.9.dist-info/RECORD
