Metadata-Version: 2.1
Name: ResiSim
Version: 2.0.9
Summary: ResiSim: A click and run plugin for future weather, extreme weather, and power outage data download.
Home-page: https://github.com/Bugs-Owner/RESI-One-click-for-future-building-energy-simulation.git
Author: Zixin Jiang
Author-email: zjiang19@syr.edu
Classifier: Programming Language :: Python :: 3
Classifier: License :: OSI Approved :: MIT License
Classifier: Operating System :: OS Independent
Requires-Python: >=3.6
License-File: LICENSE
Requires-Dist: google-auth
Requires-Dist: google-auth-oauthlib
Requires-Dist: google-auth-httplib2
Requires-Dist: google-api-python-client
Requires-Dist: numpy
Requires-Dist: pandas
Requires-Dist: matplotlib
Requires-Dist: requests
